datapress/__init__.py
datapress/client.py
tests/__init__.py
tests/conftest.py
tests/test_client.py
tests/test_integration.py
datapress-1.3.0.dist-info/METADATA
datapress-1.3.0.dist-info/WHEEL
datapress-1.3.0.dist-info/top_level.txt
datapress-1.3.0.dist-info/RECORD
